pyspeexaec.cp38-win_amd64.pyd
pyspeexaec-0.2.dist-info/METADATA
pyspeexaec-0.2.dist-info/WHEEL
pyspeexaec-0.2.dist-info/top_level.txt
pyspeexaec-0.2.dist-info/RECORD
